[
    {
        "category":"Rap Lyrics for Instagram Captions",
        "captions":[
            "“I’m not a businessman, I’m a business, man”",
            "“You only get one shot, do not miss your chance to blow. This opportunity comes once in a lifetime.”",
            "California love",
            "“We gonna party like it’s your birthday”",
            "“I got 99 problems, but [fill in the blank] ain’t one”",
            "“The more money we come across, the more problems we see”",
            "Big poppa",
            "“Drop it like it’s hot”",
            "Only God Can Judge Me",
            "“I’m feelin’ myself”",
            "“To live doesn’t mean you’re alive”"
        ]
    },
    {
        "category":"Cardi B Instagram Captions",
        "captions":[
            "“If a girl have beef with me, she gon’ have beef with me forever”",
            "“Knock me down 10 times but I get up 10”",
            "“I’m being nice to you. Have I stabbed you? No.”",
            "“I’m my own competition – I’m competing with myself.”",
            "“Do whatever you have to do. People always want to tell you how to do it. No, do it your way. And don’t ask for like oh how can you do it … do it, figure it out. I figured it out one way or another and I did it.”",
            "“I’m the rose that came from concrete.”",
            "“I’m gonna be on a budget until the day I die.”",
            "“I’m living my best life”",
            "“Looking like a right swipe on Tinder.”",
            "“Now I like dollars, I like diamonds, I like stunting, I like shining”"
        ]
    },
    {
        "category":"Instagram Captions Lyrics 2019",
        "captions":[
            "“I’ve loved and I’ve lost but that’s not what I see” – Ariana Grande",
            "“I need somebody who can take control” – Sam Smith",
            "“Keep switchin’ your alibi, or stutterin’ when you reply. You can’t even look me in the eye. Oh, I can tell, I know you’re lyin’” – The Chainsmokers",
            "“Farewell tequila, so long margarita. And lady sativa, I hate to leave ya” – Bebe Rexha",
            "“You know what you’re doin’ to me” – Ariana Grande",
            "“It’s a hard time finding your freedom” – Slushii",
            "“I would sell my soul for a bit more time” – Halsey",
            "“Always wanted to be one of those people in the room that says something and everyone puts their hand up” – Julia Michaels feat. Selena Gomez",
            "“I’m a babe, I’m a boss and I’m makin’ this money” – Avril Lavigne feat. Nicki Minaj",
            "“It was you who taught me living is togetherness” – Calvin Harris feat. Rag’n’Bone Man"
        ]
    },
    {
        "category":"Instagram Captions Travel",
        "captions":[
            "If you could travel anywhere in the world, where would you go first?",
            "Hope you’re enjoying work, I’ll just be chillin’ here in [destination]",
            "Leavin’ on a jet plane",
            "Guess where I am",
            "Work. Save. Travel. Repeat.",
            "Time for an adventure!",
            "Wanderlust",
            "Wouldn’t wanna be anywhere else",
            "Be right back, exploring the world",
            "I travel because you can always get more money, but you can never get more time",
            "Just gonna cross this off the bucket list…"
        ]
    },
    {
        "category":"Instagram Captions Vacation",
        "captions":[
            "Vacation calories don’t count",
            "Adventure, here we come!",
            "Memories made together, last forever",
            "Life is better with the sand between your toes",
            "It’s not polite to keep a vacation waiting",
            "Sorry, out on a beach relaxing. Be back soon!",
            "The only vacation you’ll ever regret is the one you don’t take",
            "Passports and palm trees",
            "BEACH: Best Escape Anyone Can Have",
            "“If you think adventure is dangerous; try routine. It’s lethal.” – Paulo Coelho"
        ]
    }
]